[{"name":"Reliability","name_pretty":false,"description":"The review is considered reliable, as opposed to reporting unreliable information","example":false,"gold":true,"pairwise":false,"justification":false,"url":false,"scale":{"type":"categorical","multiple_selection":false,"mapping":[{"label":" Completely Disagree:","description":"the review provides unreliable or untrustworthy information","value":"-2"},{"label":"Partially Disagree:","description":"the review has some unreliable information","value":"-1"},{"label":"Neutral:","description":"the review's reliability cannot be definitively determined","value":"0"},{"label":"Partially Agree:","description":"the review is mostly reliable","value":"1"},{"label":" Completely Agree:","description":"the review is entirely reliable and considered trustworthy","value":"2"}],"instructions":false},"style":{"position":"middle","orientation":"vertical","type":"list","separator":false}},{"name":"Neutrality","name_pretty":false,"description":"The review is expressed in objective terms, as opposed to resulting subjective or biased","example":false,"gold":true,"pairwise":false,"justification":false,"url":false,"scale":{"type":"categorical","multiple_selection":false,"mapping":[{"label":" Completely Disagree:","description":"the review is highly subjective or biased, providing unreliable information","value":"-2"},{"label":"Partially Disagree:","description":"the review has some elements of neutrality but also contains subjective or biased expressions","value":"-1"},{"label":"Neutral:","description":"the neutrality of the review cannot be definitively determined","value":"0"},{"label":"Partially Agree:","description":"the review is mostly expressed in objective terms but may have some subjective elements","value":"1"},{"label":" Completely Agree:","description":"the review is entirely neutral, expressed objectively without bias","value":"2"}],"instructions":false},"style":{"position":"middle","orientation":"vertical","type":"list","separator":false}},{"name":"Precision","name_pretty":false,"description":"The review is precise/specific, as opposed to vague","example":false,"gold":true,"pairwise":false,"justification":false,"url":false,"scale":{"type":"categorical","multiple_selection":false,"mapping":[{"label":" Completely Disagree:","description":"the review provides imprecise and vague information","value":"-2"},{"label":"Partially Disagree:","description":"the review contains some imprecise details and vagueness","value":"-1"},{"label":"Neutral:","description":"the review's precision cannot be definitively determined","value":"0"},{"label":"Partially Agree:","description":"the review is mostly precise, with some specific details","value":"1"},{"label":" Completely Agree:","description":"the review is entirely precise and considered trustworthy","value":"2"}],"instructions":false},"style":{"position":"middle","orientation":"vertical","type":"list","separator":false}},{"name":"Completeness","name_pretty":false,"description":"The review is complete as opposed to partial","example":false,"gold":true,"pairwise":false,"justification":false,"url":false,"scale":{"type":"categorical","multiple_selection":false,"mapping":[{"label":" Completely Disagree:","description":"the review is deficient in crucial details, presenting an incomplete overview","value":"-2"},{"label":"Partially Disagree:","description":"the review includes some details, but overall, it is incomplete","value":"-1"},{"label":"Neutral:","description":"the completeness of the review cannot be definitively determined","value":"0"},{"label":"Partially Agree:","description":"the review is mostly complete in providing necessary details","value":"1"},{"label":" Completely Agree:","description":"the review provides a comprehensive overview","value":"2"}],"instructions":false},"style":{"position":"middle","orientation":"vertical","type":"list","separator":false}},{"name":"Informativeness","name_pretty":false,"description":"The review allows deriving useful information as opposed to well-known facts and/or tautologies","example":false,"gold":true,"pairwise":false,"justification":false,"url":false,"scale":{"type":"categorical","multiple_selection":false,"mapping":[{"label":" Completely Disagree:","description":"the review lacks informative content, providing insufficient details","value":"-2"},{"label":"Partially Disagree:","description":"the review has some informative elements, but overall, it is not fully detailed","value":"-1"},{"label":"Neutral:","description":"the informativeness of the review cannot be definitively determined","value":"0"},{"label":"Partially Agree:","description":"the review is mostly informative, offering relevant details","value":"1"},{"label":" Completely Agree:","description":"the review is entirely informative, delivering a comprehensive and detailed analysis","value":"2"}],"instructions":false},"style":{"position":"middle","orientation":"vertical","type":"list","separator":false}},{"name":"Confidence","name_pretty":false,"description":"How confident do you feel about the answers you provided? Please select a corresponding number","example":"0 means completely not confident and 100 means sure","gold":false,"pairwise":false,"justification":{"text":"Write at least 10 words justifying the entered value.","min_words":10},"url":false,"scale":{"type":"interval","min":"","max":100,"step":1,"instructions":false},"style":{"position":"bottom","type":"list","orientation":"vertical","separator":false}}]